{
    "bookingLevelOne": {
        "tollAPI": {
            "status": "OK",
            "hasTolls": true,
            "duration": "367.1 km",
            "distance": "9 h 6 min",
            "tolls": [
                {
                    "id": 1030052,
                    "lat": 12.906471930202528,
                    "lng": 78.95250547618598,
                    "name": "Palligonda",
                    "road": "NH4",
                    "state": "Tamil Nadu",
                    "tagCost": 75,
                    "gmap": "https://www.google.com/maps/?saddr=43.6419434,-79.3831512&daddr=19.3299977,-98.9424832+to:19.4684923,-99.007287+to:19.996351,-99.4836581+to:19.9945164,-99.4928634+to:19.8391736,-99.871366+to:19.7029493,-101.1936502&via=1,2,3,4,5"
                },
                {
                    "id": 103023,
                    "lat": 12.648633360362194,
                    "lng": 78.58340228457101,
                    "name": "Vaniyambadi",
                    "road": "NH4",
                    "state": "Tamil Nadu",
                    "tagCost": 55,
                    "gmap": "https://www.google.com/maps/?saddr=43.6419434,-79.3831512&daddr=19.3299977,-98.9424832+to:19.4684923,-99.007287+to:19.996351,-99.4836581+to:19.9945164,-99.4928634+to:19.8391736,-99.871366+to:19.7029493,-101.1936502&via=1,2,3,4,5"
                }
            ],
            "route": [
                {
                    "location": {
                        "lat": 37.01487,
                        "lng": -7.93424
                    },
                    "address": "Philadelphia , Pennsylvania"
                },
                {
                    "location": {
                        "lat": 38.01874,
                        "lng": -7.86654
                    },
                    "address": "Bridgewater Township , New Jersey"
                },
                {
                    "location": {
                        "lat": 38.72639,
                        "lng": -9.14949
                    },
                    "address": "New York ,NY"
                }
            ]
        }
    },
    "actualTollAPINOTUSED": {
        "status": "OK",
        "summary": {
            "route": [
                {
                    "location": {
                        "lat": 37.01487,
                        "lng": -7.93424
                    },
                    "address": "Philadelphia , Pennsylvania"
                },
                {
                    "location": {
                        "lat": 38.01874,
                        "lng": -7.86654
                    },
                    "address": "Bridgewater Township , New Jersey"
                },
                {
                    "location": {
                        "lat": 38.72639,
                        "lng": -9.14949
                    },
                    "address": "New York ,NY"
                }
            ],
            "rates": {
                "USD": 1,
                "CAD": 1.282985,
                "MXN": 20.281435,
                "INR": 73.069503,
                "AUD": 1.30701,
                "GBP": 0.730355,
                "EUR": 0.827435,
                "NOK": 8.55952,
                "SEK": 8.40025,
                "DKK": 6.15375,
                "PEN": 6.15375,
                "COP": 6.15375,
                "ARS": 6.15375,
                "CLF": 6.15375,
                "CLP": 6.15375,
                "SOL": 6.15375
            },
            "departure_time": 1609507347,
            "fuelPrice": "{\"value\":2.79,\"currency\":\"INR\"}",
            "fuelEfficiency": {
                "city": 28.57,
                "hwy": 22.4,
                "units": "mpg"
            },
            "vehicleType": "2AxlesTruck",
            "share": {}
        },
        "routes": [
            {
                "summary": {
                    "hasTolls": true,
                    "diffs": "{\"cheapest\":\"0\",\"fastest\":\"7\"}",
                    "url": "https://www.google.com/maps/?saddr=43.6419434,-79.3831512&daddr=19.3299977,-98.9424832+to:19.4684923,-99.007287+to:19.996351,-99.4836581+to:19.9945164,-99.4928634+to:19.8391736,-99.871366+to:19.7029493,-101.1936502&via=1,2,3,4,5",
                    "duration": "{\"text\":\"228.1 mi\",\"metric\":\"367.1 km\",\"value\":367050}",
                    "distance": "{\"text\":\"9 h 6 min\",\"value\":32774}",
                    "name": "I-95",
                    "note": []
                },
                "costs": {
                    "fuel": 81.5,
                    "tag": 8.32,
                    "cash": null,
                    "licensePlate": 47.26,
                    "creditCard": null,
                    "prepaidCard": 8.32
                },
                "tolls": [
                    {
                        "id": 1030052,
                        "lat": 43.82105,
                        "lng": -79.47425,
                        "name": "Pennsylvania Tpke",
                        "road": "New Jersey Tpke",
                        "state": "New Jersey",
                        "country": "USA",
                        "type": "ticketSystem2",
                        "tagCost": 6.66,
                        "tagPriCost": 6.66,
                        "tagSecCost": 0,
                        "cashCost": 0,
                        "licensePlateCost": 45.6,
                        "prepaidCardCost": 6.66,
                        "creditCardCost": 6.66,
                        "currency": "USD",
                        "tagPrimary": [
                            "E-ZPass"
                        ],
                        "tagSecondary": [
                            "E-ZPass MA",
                            "E-ZPass NH",
                            "E-ZPass NY",
                            "E-ZPass NC",
                            "E-ZPass OH",
                            "E-ZPass PA",
                            "E-ZPass RI",
                            "E-ZPass VA",
                            "E-ZPass WV",
                            "E-ZPass",
                            "Uni",
                            "I-Pass",
                            "E-ZPass Skyway",
                            "E-ZPass IN",
                            "RiverLink",
                            "E-ZPass ME",
                            "E-ZPass MD"
                        ],
                        "licensePlatePrimary": "Tolls by Mail",
                        "licensePlateSecondary": null,
                        "discountCarDetails": null,
                        "discountCarType": null,
                        "discountTruckDetails": null,
                        "discountTrucks": null,
                        "height": null
                    }
                ],
                "directions": [
                    {
                        "position": {
                            "latitude": 43.64539434,
                            "longitude": -79.3831512
                        },
                        "maneuver": "forward",
                        "html_instructions": "Head toward <span class=\\\"toward_street\\\">Praça Dom Francisco Gomes</span> on <span class=\\\"street\\\">Rua da Misericórdia</span>. <span class=\\\"distance-description\\\">Go for <span class=\\\"length\\\">200 ft</span>.</span>",
                        "distance": 183,
                        "duration": 45,
                        "note": []
                    }
                ],
                "herePath": [
                    43.64539434,
                    -79.3831512,
                    43.6418318,
                    -79.3824604,
                    "..."
                ],
                "hos": {
                    "summary": "{\"total_drive_duration\":{\"text\":\"9 h 4 m\",\"value\":32679},\"total_break_duration\":{\"text\":30 m,\"value\":1800},\"total_duration\":{\"text\":9 h 34 m\",\"value\":34479},\"total_distance\":{\"text\":228,\"metric\":367,\"value\":367050},\"rulesParam\":{\"rule\":60,\"dutyHoursBeforeEndOfWorkDay\":11,\"dutyHoursBeforeRestBreak\":7,\"drivingHoursBeforeEndOfWorkDay\":11,\"timeRemaining\":60}}",
                    "break_points": [
                        43.78465,
                        -79.52755
                    ],
                    "stops": [
                        []
                    ],
                    "data": [
                        {
                            "instruction": "Start from Philadelphia , Pennsylvania"
                        },
                        {
                            "instruction": "Drive",
                            "duration": {
                                "text": "1 h 41 m",
                                "value": 6106
                            },
                            "distance": {
                                "text": 19,
                                "metric": 30,
                                "value": 29836
                            }
                        },
                        {
                            "instruction": "Break",
                            "duration": {
                                "text": "30 m",
                                "value": 1800
                            }
                        }
                    ]
                }
            }
        ]
    },
    "bookingLeveltwo": {
        "status": true,
        "msg": "Order placed successfully"
    }
}